[
  {
    "id": "course-cs101",
    "code": "CS101",
    "name": "Introduction to Computer Science",
    "term": "Fall 2025",
    "description": "Fundamental concepts in computer science including programming, algorithms, and data structures.",
    "instructorIds": ["user-1"],
    "enrollmentCount": 156,
    "status": "active",
    "createdAt": "2025-08-15T00:00:00Z"
  },
  {
    "id": "course-cs201",
    "code": "CS201",
    "name": "Data Structures and Algorithms",
    "term": "Fall 2025",
    "description": "Advanced data structures, algorithm design, and complexity analysis.",
    "instructorIds": ["user-1"],
    "enrollmentCount": 89,
    "status": "active",
    "createdAt": "2025-08-15T00:00:00Z"
  },
  {
    "id": "course-cs301",
    "code": "CS301",
    "name": "Advanced Algorithms",
    "term": "Fall 2025",
    "description": "Graph algorithms, dynamic programming, NP-completeness, and approximation algorithms.",
    "instructorIds": ["demo-instructor-1"],
    "enrollmentCount": 45,
    "status": "active",
    "createdAt": "2025-08-15T00:00:00Z"
  },
  {
    "id": "course-math221",
    "code": "MATH221",
    "name": "Calculus I",
    "term": "Fall 2025",
    "description": "Limits, derivatives, integrals, and applications.",
    "instructorIds": ["user-1"],
    "enrollmentCount": 203,
    "status": "active",
    "createdAt": "2025-08-15T00:00:00Z"
  },
  {
    "id": "course-math341",
    "code": "MATH341",
    "name": "Linear Algebra",
    "term": "Fall 2025",
    "description": "Vector spaces, matrices, eigenvalues, and linear transformations.",
    "instructorIds": ["demo-instructor-1"],
    "enrollmentCount": 78,
    "status": "active",
    "createdAt": "2025-08-15T00:00:00Z"
  },
  {
    "id": "course-phys141",
    "code": "PHYS141",
    "name": "Classical Mechanics",
    "term": "Fall 2025",
    "description": "Newton's laws, energy, momentum, rotational dynamics, and oscillations.",
    "instructorIds": ["user-1"],
    "enrollmentCount": 112,
    "status": "active",
    "createdAt": "2025-08-15T00:00:00Z"
  }
]
